.svnignore
CHANGES.txt
CONTRIBUTORS.txt
README.txt
setup.cfg
setup.py
docs/HISTORY.txt
docs/INSTALL.txt
docs/LICENSE.EUPL
docs/LICENSE.GPL
docs/LICENSE.txt
slc/__init__.py
slc.shoppinglist.egg-info/PKG-INFO
slc.shoppinglist.egg-info/SOURCES.txt
slc.shoppinglist.egg-info/dependency_links.txt
slc.shoppinglist.egg-info/entry_points.txt
slc.shoppinglist.egg-info/namespace_packages.txt
slc.shoppinglist.egg-info/not-zip-safe
slc.shoppinglist.egg-info/requires.txt
slc.shoppinglist.egg-info/top_level.txt
slc/shoppinglist/README.txt
slc/shoppinglist/__init__.py
slc/shoppinglist/configure.zcml
slc/shoppinglist/interfaces.py
slc/shoppinglist/shoppinglist.py
slc/shoppinglist/shoppinglist_icon.gif
slc/shoppinglist/widget.pt
slc/shoppinglist/widget.py
slc/shoppinglist/profiles/default/actions.xml
slc/shoppinglist/profiles/default/memberdata_properties.xml
slc/shoppinglist/tests/__init__.py
slc/shoppinglist/tests/base.py
slc/shoppinglist/tests/test_basic.py