Metadata-Version: 1.0
Name: slc.shoppinglist
Version: 1.5
Summary: A shoppinglist of UIDs
Home-page: http://www.syslab.com
Author: syslab.com
Author-email: thomas@syslab.com
License: GPL + EUPL
Platform: UNKNOWN
Classifier: Framework :: Plone
Classifier: Programming Language :: Python
Classifier: Topic :: Software Development :: Libraries :: Python Modules
Classifier: License :: OSI Approved :: GNU General Public License (GPL)
Classifier: License :: OSI Approved :: European Union Public Licence 1.1 (EUPL 1.1)
